Metadata-Version: 2.1
Name: dj-migration-test
Version: 0.4.0
Summary: Django migration test module
Home-page: https://github.com/philsupertramp/dj-migration-test
Download-URL: https://github.com/philsupertramp/dj-migration-test/archive/0.4.0.tar.gz
Author: Philipp Zettl
Author-email: philipp.zettl@godesteem.de
License: MIT
Keywords: Django,Testing,Database
Classifier: Development Status :: 4 - Beta
Classifier: Intended Audience :: Developers
Classifier: Topic :: Software Development :: Bug Tracking
Classifier: License :: OSI Approved :: MIT License
Classifier: Programming Language :: Python :: 3
Classifier: Programming Language :: Python :: 3.10
Classifier: Programming Language :: Python :: 3.9
Classifier: Programming Language :: Python :: 3.8
Classifier: Operating System :: OS Independent
License-File: LICENSE.txt
